sphinx_collapse/__init__.py
sphinx_collapse/_static/sphinx_collapse.css
sphinx_collapse-0.1.2.dist-info/LICENSE.md
sphinx_collapse-0.1.2.dist-info/WHEEL
sphinx_collapse-0.1.2.dist-info/METADATA
sphinx_collapse-0.1.2.dist-info/RECORD
