Metadata-Version: 2.1
Name: sphinx_collapse
Version: 0.1.2
Summary: Collapse extension for Sphinx.
Home-page: https://github.com/dgarcia360/sphinx-collapse
Author: David Garcia
Author-email: hi@davidgarcia.dev
Requires-Python: >=3.7
Requires-Dist: sphinx >= 3
Requires-Dist: alabaster ; extra == "doc"
Requires-Dist: pre-commit ; extra == "test"
Requires-Dist: pytest ; extra == "test"
Provides-Extra: doc
Provides-Extra: test
